django_translatemessages/__init__.py
django_translatemessages/management/__init__.py
django_translatemessages/management/commands/__init__.py
django_translatemessages/management/commands/translatemessages.py
django_translatemessages-0.0.6.dist-info/LICENSE
django_translatemessages-0.0.6.dist-info/METADATA
django_translatemessages-0.0.6.dist-info/WHEEL
django_translatemessages-0.0.6.dist-info/top_level.txt
django_translatemessages-0.0.6.dist-info/RECORD
